cs/delta.py
cs.delta-20240622.dist-info/METADATA
cs.delta-20240622.dist-info/WHEEL
cs.delta-20240622.dist-info/top_level.txt
cs.delta-20240622.dist-info/RECORD
