Metadata-Version: 2.1
Name: cs.delta
Version: 20240622
Summary: Utility functions around state changes.
Author-email: Cameron Simpson <cs@cskk.id.au>
License: GNU General Public License v3 or later (GPLv3+)
Project-URL: Monorepo Hg/Mercurial Mirror, https://hg.sr.ht/~cameron-simpson/css
Project-URL: Monorepo Git Mirror, https://github.com/cameron-simpson/css
Project-URL: MonoRepo Commits, https://bitbucket.org/cameron_simpson/css/commits/all
Project-URL: Source, https://github.com/cameron-simpson/css/blob/main/lib/python/cs/delta.py
Keywords: python2,python3
Platform: UNKNOWN
Classifier: Programming Language :: Python
Classifier: Programming Language :: Python :: 3
Classifier: Development Status :: 4 - Beta
Classifier: Intended Audience :: Developers
Classifier: Operating System :: OS Independent
Classifier: Topic :: Software Development :: Libraries :: Python Modules
Classifier: License :: OSI Approved :: GNU General Public License v3 or later (GPLv3+)
Requires-Dist: cs.obj >=20220918
Requires-Dist: cs.resources >=20240522
Requires-Dist: icontract
